medusa/__init__.py
medusa/medusa.py
python_medusa-1.0.1.dist-info/LICENSE
python_medusa-1.0.1.dist-info/METADATA
python_medusa-1.0.1.dist-info/WHEEL
python_medusa-1.0.1.dist-info/top_level.txt
python_medusa-1.0.1.dist-info/RECORD
